ltst_noodles-0.0.3.dist-info/LICENSE.txt
ltst_noodles-0.0.3.dist-info/METADATA
ltst_noodles-0.0.3.dist-info/RECORD
ltst_noodles-0.0.3.dist-info/WHEEL
ltst_noodles-0.0.3.dist-info/top_level.txt
noodles/__init__.py
noodles/actions.py
